[
  {
    "file_name": "11.jpg",
    "size": "x"
  },
  {
    "file_name": "1.jpg",
    "size": "x"
  },
  {
    "file_name": "7.jpg",
    "size": "x"
  },
  {
    "file_name": "9.jpg",
    "size": "x"
  },
  {
    "file_name": "1301013483_1.jpg",
    "size": "x"
  },
  {
    "file_name": "10.jpg",
    "size": "y"
  },
  {
    "file_name": "5.jpg",
    "size": "x"
  },
  {
    "file_name": "8.jpg",
    "size": "x"
  },
  {
    "file_name": "19.jpg",
    "size": "y"
  },
  {
    "file_name": "18.jpg",
    "size": "y"
  },
  {
    "file_name": "3.jpg",
    "size": "z"
  },
  {
    "file_name": "1315528167_8.jpg",
    "size": "y"
  },
  {
    "file_name": "27.jpg",
    "size": "y"
  },
  {
    "file_name": "1319829391_8.jpg",
    "size": "z"
  },
  {
    "file_name": "12.jpg",
    "size": "z"
  },
  {
    "file_name": "16.jpg",
    "size": "z"
  },
  {
    "file_name": "14.jpg",
    "size": "x"
  },
  {
    "file_name": "1319844309_9.jpg",
    "size": "x"
  },
  {
    "file_name": "1319844323_5.jpg",
    "size": "x"
  },
  {
    "file_name": "15.jpg",
    "size": "z"
  },
  {
    "file_name": "1323907366_8.jpg",
    "size": "z"
  },
  {
    "file_name": "1323907386_1.jpg",
    "size": "z"
  },
  {
    "file_name": "4.jpg",
    "size": "z"
  },
  {
    "file_name": "1323907734_5.jpg",
    "size": "z"
  },
  {
    "file_name": "1323907745_4.jpg",
    "size": "z"
  },
  {
    "file_name": "0.jpg",
    "size": "z"
  },
  {
    "file_name": "1323907772_1.jpg",
    "size": "z"
  },
  {
    "file_name": "1324136565_3.jpg",
    "size": "x"
  },
  {
    "file_name": "1325337157_5.jpg",
    "size": "y"
  },
  {
    "file_name": "1325337173_7.jpg",
    "size": "x"
  },
  {
    "file_name": "45.jpg",
    "size": "y"
  },
  {
    "file_name": "1327097474_8.jpg",
    "size": "x"
  },
  {
    "file_name": "1327501186_19.jpg",
    "size": "x"
  },
  {
    "file_name": "1327970296_9.jpg",
    "size": "y"
  },
  {
    "file_name": "25.jpg",
    "size": "z"
  },
  {
    "file_name": "1328608204_8.jpg",
    "size": "y"
  },
  {
    "file_name": "20.jpg",
    "size": "y"
  },
  {
    "file_name": "28.jpg",
    "size": "y"
  },
  {
    "file_name": "23.jpg",
    "size": "x"
  },
  {
    "file_name": "26.jpg",
    "size": "y"
  },
  {
    "file_name": "1329593923_11.jpg",
    "size": "z"
  },
  {
    "file_name": "1330765761_1.jpg",
    "size": "x"
  },
  {
    "file_name": "1332317724_9.jpg",
    "size": "x"
  },
  {
    "file_name": "1332521411_9.jpg",
    "size": "y"
  },
  {
    "file_name": "41.jpg",
    "size": "x"
  },
  {
    "file_name": "2.jpg",
    "size": "y"
  },
  {
    "file_name": "39.jpg",
    "size": "z"
  },
  {
    "file_name": "17.jpg",
    "size": "z"
  },
  {
    "file_name": "1339176922_9.jpg",
    "size": "y"
  },
  {
    "file_name": "1340196275_4.jpg",
    "size": "x"
  },
  {
    "file_name": "1344268826_7.jpg",
    "size": "z"
  },
  {
    "file_name": "1348253256_7.jpg",
    "size": "x"
  },
  {
    "file_name": "1349819995_8.jpg",
    "size": "y"
  },
  {
    "file_name": "1351711613_3.jpg",
    "size": "x"
  }
]